CHANGES.rst
DESCRIPTION.rst
LICENSE
MANIFEST.in
README.md
setup.py
src/wai.annotations.adams.egg-info/PKG-INFO
src/wai.annotations.adams.egg-info/SOURCES.txt
src/wai.annotations.adams.egg-info/dependency_links.txt
src/wai.annotations.adams.egg-info/entry_points.txt
src/wai.annotations.adams.egg-info/namespace_packages.txt
src/wai.annotations.adams.egg-info/requires.txt
src/wai.annotations.adams.egg-info/top_level.txt
src/wai/annotations/adams/__init__.py
src/wai/annotations/adams/constants.py
src/wai/annotations/adams/base/__init__.py
src/wai/annotations/adams/base/component/_ADAMSBaseReader.py
src/wai/annotations/adams/base/component/_ADAMSBaseWriter.py
src/wai/annotations/adams/base/component/_ADAMSFilenameSource.py
src/wai/annotations/adams/base/component/__init__.py
src/wai/annotations/adams/ic/__init__.py
src/wai/annotations/adams/ic/component/_FromADAMS.py
src/wai/annotations/adams/ic/component/_ToADAMS.py
src/wai/annotations/adams/ic/component/__init__.py
src/wai/annotations/adams/ic/specifier/_ADAMSICInputFormatSpecifier.py
src/wai/annotations/adams/ic/specifier/_ADAMSICOutputFormatSpecifier.py
src/wai/annotations/adams/ic/specifier/__init__.py
src/wai/annotations/adams/od/__init__.py
src/wai/annotations/adams/od/component/_FromADAMSReport.py
src/wai/annotations/adams/od/component/_ToADAMSReport.py
src/wai/annotations/adams/od/component/__init__.py
src/wai/annotations/adams/od/specifier/_ADAMSODInputFormatSpecifier.py
src/wai/annotations/adams/od/specifier/_ADAMSODOutputFormatSpecifier.py
src/wai/annotations/adams/od/specifier/__init__.py
src/wai/annotations/adams/util/__init__.py
src/wai/annotations/adams/util/_format.py
src/wai/annotations/adams/util/_prefixes.py